autostack_cli/__init__.py
autostack_cli/cli.py
autostack_cli/agents/__init__.py
autostack_cli/agents/base.py
autostack_cli/agents/build_agent.py
autostack_cli/commands/__init__.py
autostack_cli/commands/build.py
autostack_cli/services/__init__.py
autostack_cli/services/llm_service.py
autostack_cli/services/project_state.py
autostack_cli/templates/prompts/auth.txt
autostack_cli/templates/prompts/data.txt
autostack_cli/templates/prompts/init.txt
autostack_cli/templates/prompts/init_ui.txt
autostack_cli/templates/prompts/sql_migrations.txt
autostack_cli/templates/prompts/system.txt
autostack_cli/tools/__init__.py
autostack_cli/tools/build_tools.py
autostack_cli/tools/constants.py
autostack_cli/tools/env_tools.py
autostack_cli/tools/npm_tools.py
autostack_cli/tools/sql_tools.py
autostack_cli/utils/__init__.py
autostack_cli/utils/config.py
autostack_cli/utils/progress.py
autostack_cli/utils/project_utils.py
autostack_cli-1.0.0.dist-info/METADATA
autostack_cli-1.0.0.dist-info/WHEEL
autostack_cli-1.0.0.dist-info/entry_points.txt
autostack_cli-1.0.0.dist-info/licenses/license
autostack_cli-1.0.0.dist-info/RECORD
