Metadata-Version: 2.4
Name: autostack-cli
Version: 1.0.0
Summary: AI-powered CLI tool for build your full-stack  applications in minutes
License-File: license
Keywords: AI,Agent,CLI,Code Generation,Full-Stack
Requires-Python: >=3.10
Requires-Dist: anthropic>=0.18.1
Requires-Dist: flask-cors==4.0.0
Requires-Dist: flask-jwt-extended==4.5.2
Requires-Dist: flask-migrate==4.0.5
Requires-Dist: flask-sqlalchemy==3.1.1
Requires-Dist: flask==2.3.3
Requires-Dist: google-generativeai>=0.5.0
Requires-Dist: json-repair>=0.30.0
Requires-Dist: openai>=1.12.0
Requires-Dist: python-dotenv>=1.0.0
Requires-Dist: rich>=13.7.0
Requires-Dist: sqlalchemy==2.0.23
Requires-Dist: typer>=0.9.0
Requires-Dist: werkzeug==2.3.7
